dataverk/__init__.py
dataverk/datapackage.py
dataverk/dataverk.py
dataverk/dataverk_context.py
dataverk/abc/__init__.py
dataverk/abc/base.py
dataverk/connectors/__init__.py
dataverk/connectors/elasticsearch.py
dataverk/connectors/jsonstat.py
dataverk/connectors/kafka.py
dataverk/connectors/databases/__init__.py
dataverk/connectors/databases/base.py
dataverk/connectors/databases/db2.py
dataverk/connectors/databases/db_connector_factory.py
dataverk/connectors/databases/oracle.py
dataverk/connectors/databases/postgres.py
dataverk/connectors/databases/sqlite.py
dataverk/connectors/databases/utils/__init__.py
dataverk/connectors/databases/utils/error_strategies.py
dataverk/connectors/storage/__init__.py
dataverk/connectors/storage/bucket_storage_base.py
dataverk/connectors/storage/file_storage.py
dataverk/connectors/storage/google_storage.py
dataverk/connectors/storage/nais.py
dataverk/connectors/storage/storage_connector_factory.py
dataverk/connectors/storage/utils/__init__.py
dataverk/connectors/storage/utils/blob_metadata.py
dataverk/context/__init__.py
dataverk/context/env_store.py
dataverk/context/replacer.py
dataverk/context/settings_classes.py
dataverk/context/values_importer.py
dataverk/exceptions/__init__.py
dataverk/exceptions/dataverk_exceptions.py
dataverk/resources/__init__.py
dataverk/resources/base_resource.py
dataverk/resources/dataframe_resource.py
dataverk/resources/factory_resources.py
dataverk/resources/json_resource.py
dataverk/resources/pdf_resource.py
dataverk/resources/remote_resource.py
dataverk/utils/__init__.py
dataverk/utils/anonymization.py
dataverk/utils/file_functions.py
dataverk/utils/logger.py
dataverk/utils/mapping_util.py
dataverk/utils/metadata_utils.py
dataverk/utils/storage_paths.py
dataverk/utils/validators.py
dataverk/views/__init__.py
dataverk/views/base.py
dataverk/views/datatable_spec.py
dataverk/views/default.py
dataverk/views/json_spec.py
dataverk/views/remote_spec.py
dataverk/views/view_factory.py
dataverk-0.4.17.dist-info/LICENSE.md
dataverk-0.4.17.dist-info/METADATA
dataverk-0.4.17.dist-info/WHEEL
dataverk-0.4.17.dist-info/top_level.txt
dataverk-0.4.17.dist-info/RECORD
