Metadata-Version: 2.1
Name: dataverk
Version: 0.4.17
Summary: Serverless ETL framework
Home-page: https://github.com/navikt
Author: NAV IKT
Author-email: paul.bencze@nav.no
License: MIT
Project-URL: Bug Tracker, https://github.com/navikt
Project-URL: Documentation, https://github.com/navikt
Project-URL: Source Code, https://github.com/navikt
Keywords: datapackage serverless etl jupyter open-data
Platform: UNKNOWN
Classifier: Development Status :: 3 - Alpha
Classifier: License :: OSI Approved :: MIT License
Classifier: Programming Language :: Python :: 3.6
Classifier: Programming Language :: Python :: 3.7
Requires-Python: >=3.6
License-File: LICENSE.md
Requires-Dist: data-catalog-dcat-validator (>=0.0.5)
Requires-Dist: dataverk-vault (>=0.1.9)
Requires-Dist: dataverk-gsm (>=0.0.2)
Requires-Dist: dataverk-publisher (>=0.0.8)
Requires-Dist: google-auth (>=1.26.1)
Requires-Dist: google-cloud-storage (>=1.36.1)
Requires-Dist: avro-python3 (==1.9.2.1)
Requires-Dist: SQLAlchemy (>=1.3.20)
Requires-Dist: pyjstat (>=2.2.0)
Requires-Dist: psycopg2 (>=2.8.6)
Requires-Dist: pandas (>=1.1.4)
Requires-Dist: cx-Oracle (>=8.0.1)
Requires-Dist: protobuf (>=3.14.0)
Requires-Dist: sphinx-rtd-theme (>=0.5.0)
Requires-Dist: Sphinx (>=3.3.1)
Requires-Dist: nbsphinx (>=0.8.0)
Requires-Dist: kafka-python (>=2.0.2)
Requires-Dist: streamz (>=0.6.2)
Requires-Dist: urllib3 (>=1.26.2)
Requires-Dist: rsa (>=4.7)
Requires-Dist: mistune (>=2.0.1)
